Workbook
Name IQ_CH: 110000
Name IQ_CQ: 5000
Name IQ_CY: 10000
Name IQ_DAILY: 500000
Name IQ_DNTM: 700000
Name IQ_FH: 100000
Name IQ_FQ: 500
Name IQ_FWD_CY: 10001
Name IQ_FWD_CY1: 10002
Name IQ_FWD_CY2: 10003
Name IQ_FWD_FY: 1001
Name IQ_FWD_FY1: 1002
Name IQ_FWD_FY2: 1003
Name IQ_FWD_Q: 501
Name IQ_FWD_Q1: 502
Name IQ_FWD_Q2: 503
Name IQ_FY: 1000
Name IQ_LATESTK: 1000
Name IQ_LATESTQ: 500
Name IQ_LTM: 2000
Name IQ_LTMMONTH: 120000
Name IQ_MONTH: 15000
Name IQ_MTD: 800000
Name IQ_NAMES_REVISION_DATE_: 45892.7620717593
Name IQ_NTM: 6000
Name IQ_QTD: 750000
Name IQ_TODAY: 0
Name IQ_WEEK: 50000
Name IQ_YTD: 3000
Name IQ_YTDMONTH: 130000

Sheet Output
D3: =Backup!N2 -> beta_market | E3: =Backup!O2 -> beta_value | F3: =Backup!P2 -> beta_momentum | G3: =Backup!Q2 -> beta_growth
C5: =Backup!M4 -> AdTech | D5: =Backup!N4 -> 1.354 | E5: =Backup!O4 -> 0.812 | F5: =Backup!P4 -> 0.058 | G5: =Backup!Q4 -> 0.058
C6: =Backup!M5 -> AI-Industrial | D6: =Backup!N5 -> 1.8662104 | E6: =Backup!O5 -> 0.06406839 | F6: =Backup!P5 -> 4.8332237 | G6: =Backup!Q5 -> -2.4677014
C7: =Backup!M6 -> Digital Infra | D7: =Backup!N6 -> 1.0298299 | E7: =Backup!O6 -> -0.32344643 | F7: =Backup!P6 -> 2.4717861 | G7: =Backup!Q6 -> -1.1219885
C8: =Backup!M7 -> Experientials | D8: =Backup!N7 -> 1.477498 | E8: =Backup!O7 -> 0.1714434 | F8: =Backup!P7 -> -1.0121211 | G8: =Backup!Q7 -> 0.50753576
C9: =Backup!M8 -> Nuclear | D9: =Backup!N8 -> 0.98209569 | E9: =Backup!O8 -> 0.43101235 | F9: =Backup!P8 -> 1.1420347 | G9: =Backup!Q8 -> 0.51883453
C10: =Backup!M9 -> Payments | D10: =Backup!N9 -> 1.0689293 | E10: =Backup!O9 -> 0.35435158 | F10: =Backup!P9 -> -1.1860926 | G10: =Backup!Q9 -> 1.1405714
C11: =Backup!M10 -> Security | D11: =Backup!N10 -> 0.87114872 | E11: =Backup!O10 -> 0.14012431 | F11: =Backup!P10 -> 0.072693717 | G11: =Backup!Q10 -> -0.21596139
C12: =Backup!M11 -> Silver | D12: =Backup!N11 -> 0.66421166 | E12: =Backup!O11 -> 0.31700827 | F12: =Backup!P11 -> -0.43761064 | G12: =Backup!Q11 -> 0.097978284
C13: =Backup!M12 -> Waste | D13: =Backup!N12 -> 0.8153752 | E13: =Backup!O12 -> 0.50105858 | F13: =Backup!P12 -> -0.49681101 | G13: =Backup!Q12 -> -0.16451659
C14: =Backup!M13 -> Thematic Portfolio (exc SPY) | D14: =Backup!N13 -> 0.7018496 | E14: =Backup!O13 -> 0.07900479 | F14: =Backup!P13 -> 0.58050613 | G14: =Backup!Q13 -> -0.27318982
D16: S&P 500 | E16: Value | F16: Momentum | G16: Growth
C17: Weekly return | D17: ='Weekly Return From Factor ETFs'!E3 -> 0.0099957744 | E17: 0.0211 | F17: x | G17: x
B19: Portfolio Level
B21: Absolute Return | C21: Total Return | D21: Beta | E21: Value | F21: Momentum | G21: Growth
B22: Thematic Fund | C22: ='Weekly Return From Factor ETFs'!E7 -> -0.0025290796 | D22: =D$14 -> 0.7018496 | E22: =E$14 -> 0.07900479 | F22: =F$14 -> 0.58050613 | G22: =G14 -> -0.27318982
B23: Factor Return | D23: =D$17 -> 0.0099957744 | E23: =E$17 -> 0.0211 | F23: =F$17 -> x | G23: =G$17 -> x
B24: Imputed Thematic Return | C24: =SUM(D24:F24) -> #VALUE! | D24: =D22*D23 -> 0.0070155303 | E24: =E22*E23 -> 0.0016670011 | F24: =F22*F23 -> #VALUE! | G24: =G22*G23 -> #VALUE!
B25: Idiosyncratic return (alpha) | C25: =C22-C24 -> #VALUE!
B27: Excess Return | C27: Total Return | D27: Beta | E27: Value | F27: Momentum
B28: Thematic Fund | C28: ='Weekly Return From Factor ETFs'!E8 -> -0.021901591 | D28: =D$14-1 -> -0.2981504 | E28: =E$14 -> 0.07900479 | F28: =F$14 -> 0.58050613
B29: Factor Return | D29: =D$17 -> 0.0099957744 | E29: =E$17 -> 0.0211 | F29: =F$17 -> x
B30: Imputed Thematic Return | C30: =SUM(D30:F30) -> #VALUE! | D30: =D28*D29 -> -0.0029802441 | E30: =E28*E29 -> 0.0016670011 | F30: =F28*F29 -> #VALUE!
B31: Idiosyncratic return (alpha) | C31: =C28-C30 -> #VALUE!

Sheet Weekly Return From Factor ETFs
A1: As of 2/25
C2: Week-ago Close (2/18) | D2: Current Close (2/25) | E2: Weekly Return | F2: IRR
B3: S&P 500 | C3: 686.29 | D3: 693.15 | E3: =D3/C3-1 -> 0.0099957744 | F3: =(D3/C3)^(1/(7/365))-1 -> 0.67970893
B4: iShares S&P 500 Value ETF (IVE) | C4: 221.01 | D4: 221.58 | E4: =D4/C4-1 -> 0.0025790688 | F4: =(D4/C4)^(1/(7/365))-1 -> 0.14374378
B5: iShares MSCI USA Momentum Factor ETF (MTUM) | C5: 253.49 | D5: 256.38 | E5: =D5/C5-1 -> 0.011400844 | F5: =(D5/C5)^(1/(7/365))-1 -> 0.80599084
B7: Fund absolute return | C7: 478241.17 | D7: 477031.66 | E7: =D7/C7-1 -> -0.0025290796 | F7: =(D7/C7)^(1/(7/365))-1 -> -0.12369448
B8: Fund excess return | C8: 845137 | D8: 826627.16 | E8: =D8/C8-1 -> -0.021901591
C10: beginning of buying, beginning of this sem
C11: irr

Sheet >>>

Sheet Backup
A2: Account Name | B2: Symbol | C2: Sector | D2: Current Value | E2: =Betas!D1 -> beta_market | F2: =Betas!E1 -> beta_value | G2: =Betas!F1 -> beta_momentum | H2: =Betas!G1 -> beta_growth | I2: Weights (Portfolio) | J2: Weights (Sub Fund) | N2: beta_market | O2: beta_value | P2: beta_momentum | Q2: beta_growth | R2: Total
A3: Corporation | B3: SPY | C3: =VLOOKUP(B3,Subsector!$A:$B,2,FALSE) -> Benchmark | D3: =iferror(vlookup(B3,'Portfolio Positions'!$A:$F,4,false),0) -> 261442 | E3: =iferror(VLOOKUP(B3,Betas!$B:$H,3,FALSE),0) -> 0.998 | F3: =iferror(VLOOKUP(B3,Betas!$B:$H,4,FALSE),0) -> -0.002 | G3: =iferror(VLOOKUP(B3,Betas!$B:$H,5,FALSE),0) -> 0.002 | H3: =iferror(VLOOKUP(B3,Betas!$B:$H,6,FALSE),0) -> -0.004 | I3: =D3/SUM($D$3:$D$67) -> 0.38336123 | J3: =IFERROR(D3 / XLOOKUP(C3, $M:$M, $R:$R), 0) -> 0
A4: Corporation | B4: ABBV | C4: =VLOOKUP(B4,Subsector!$A:$B,2,FALSE) -> Silver | D4: =iferror(vlookup(B4,'Portfolio Positions'!$A:$F,4,false),0) -> 7356.02 | E4: =iferror(VLOOKUP(B4,Betas!$B:$H,3,FALSE),0) -> 0.146 | F4: =iferror(VLOOKUP(B4,Betas!$B:$H,4,FALSE),0) -> -0.101 | G4: =iferror(VLOOKUP(B4,Betas!$B:$H,5,FALSE),0) -> 0.123 | H4: =iferror(VLOOKUP(B4,Betas!$B:$H,6,FALSE),0) -> 0.367 | I4: =D4/SUM($D$3:$D$67) -> 0.01078638 | J4: =IFERROR(D4 / XLOOKUP(C4, $M:$M, $R:$R), 0) -> 0.1246319 | M4: AdTech | N4: {=SUMPRODUCT(($C$4:$C$999=M4)*IFERROR($E$4:$E$999*$J$4:$J$999,0))} -> 1.354 | O4: {=SUMPRODUCT(($C$4:$C$999=M4)*IFERROR($F$4:$F$999*$J$4:$J$999,0))} -> 0.812 | P4: {=SUMPRODUCT(($C$4:$C$999=M4)*IFERROR($H$4:$H$999*$J$4:$J$999,0))} -> 0.058 | Q4: {=SUMPRODUCT(($C$4:$C$999=M4)*IFERROR($H$4:$H$999*$J$4:$J$999,0))} -> 0.058 | R4: =SUMIFS($D$3:$D$67,$C$3:$C$67,M4) -> 3717.07
A5: Corporation | B5: ABNB | C5: =VLOOKUP(B5,Subsector!$A:$B,2,FALSE) -> Experientials | D5: =iferror(vlookup(B5,'Portfolio Positions'!$A:$F,4,false),0) -> 8668.51 | E5: =iferror(VLOOKUP(B5,Betas!$B:$H,3,FALSE),0) -> 1.385 | F5: =iferror(VLOOKUP(B5,Betas!$B:$H,4,FALSE),0) -> -0.919 | G5: =iferror(VLOOKUP(B5,Betas!$B:$H,5,FALSE),0) -> -1.328 | H5: =iferror(VLOOKUP(B5,Betas!$B:$H,6,FALSE),0) -> -0.005 | I5: =D5/SUM($D$3:$D$67) -> 0.012710929 | J5: =IFERROR(D5 / XLOOKUP(C5, $M:$M, $R:$R), 0) -> 0.11380832 | M5: AI-Industrial | N5: {=SUMPRODUCT(($C$4:$C$999=M5)*IFERROR($E$4:$E$999*$J$4:$J$999,0))} -> 1.8662104 | O5: {=SUMPRODUCT(($C$4:$C$999=M5)*IFERROR($F$4:$F$999*$J$4:$J$999,0))} -> 0.06406839 | P5: {=SUMPRODUCT(($C$4:$C$999=M5)*IFERROR($G$4:$G$999*$J$4:$J$999,0))} -> 4.8332237 | Q5: {=SUMPRODUCT(($C$4:$C$999=M5)*IFERROR($H$4:$H$999*$J$4:$J$999,0))} -> -2.4677014 | R5: =SUMIFS($D$3:$D$67,$C$3:$C$67,M5) -> 57549.63
A6: Corporation | B6: ABT | C6: =VLOOKUP(B6,Subsector!$A:$B,2,FALSE) -> Silver | D6: =iferror(vlookup(B6,'Portfolio Positions'!$A:$F,4,false),0) -> 3401.19 | E6: =iferror(VLOOKUP(B6,Betas!$B:$H,3,FALSE),0) -> 0.649 | F6: =iferror(VLOOKUP(B6,Betas!$B:$H,4,FALSE),0) -> 0.68 | G6: =iferror(VLOOKUP(B6,Betas!$B:$H,5,FALSE),0) -> -0.548 | H6: =iferror(VLOOKUP(B6,Betas!$B:$H,6,FALSE),0) -> 0.372 | I6: =D6/SUM($D$3:$D$67) -> 0.0049872796 | J6: =IFERROR(D6 / XLOOKUP(C6, $M:$M, $R:$R), 0) -> 0.05762583 | M6: Digital Infra | N6: {=SUMPRODUCT(($C$4:$C$999=M6)*IFERROR($E$4:$E$999*$J$4:$J$999,0))} -> 1.0298299 | O6: {=SUMPRODUCT(($C$4:$C$999=M6)*IFERROR($F$4:$F$999*$J$4:$J$999,0))} -> -0.32344643 | P6: {=SUMPRODUCT(($C$4:$C$999=M6)*IFERROR($G$4:$G$999*$J$4:$J$999,0))} -> 2.4717861 | Q6: {=SUMPRODUCT(($C$4:$C$999=M6)*IFERROR($H$4:$H$999*$J$4:$J$999,0))} -> -1.1219885 | R6: =SUMIFS($D$3:$D$67,$C$3:$C$67,M6) -> 96621.6
A7: Corporation | B7: ADUS | C7: =VLOOKUP(B7,Subsector!$A:$B,2,FALSE) -> Silver | D7: =iferror(vlookup(B7,'Portfolio Positions'!$A:$F,4,false),0) -> 4805.23 | E7: =iferror(VLOOKUP(B7,Betas!$B:$H,3,FALSE),0) -> 0.679 | F7: =iferror(VLOOKUP(B7,Betas!$B:$H,4,FALSE),0) -> 1.071 | G7: =iferror(VLOOKUP(B7,Betas!$B:$H,5,FALSE),0) -> -0.478 | H7: =iferror(VLOOKUP(B7,Betas!$B:$H,6,FALSE),0) -> 0.218 | I7: =D7/SUM($D$3:$D$67) -> 0.0070460708 | J7: =IFERROR(D7 / XLOOKUP(C7, $M:$M, $R:$R), 0) -> 0.08141426 | M7: Experientials | N7: {=SUMPRODUCT(($C$4:$C$999=M7)*IFERROR($E$4:$E$999*$J$4:$J$999,0))} -> 1.477498 | O7: {=SUMPRODUCT(($C$4:$C$999=M7)*IFERROR($F$4:$F$999*$J$4:$J$999,0))} -> 0.1714434 | P7: {=SUMPRODUCT(($C$4:$C$999=M7)*IFERROR($G$4:$G$999*$J$4:$J$999,0))} -> -1.0121211 | Q7: {=SUMPRODUCT(($C$4:$C$999=M7)*IFERROR($H$4:$H$999*$J$4:$J$999,0))} -> 0.50753576 | R7: =SUMIFS($D$3:$D$67,$C$3:$C$67,M7) -> 76167.63
A8: Corporation | B8: ALRM | C8: =VLOOKUP(B8,Subsector!$A:$B,2,FALSE) -> Security | D8: =iferror(vlookup(B8,'Portfolio Positions'!$A:$F,4,false),0) -> 6684.08 | E8: =iferror(VLOOKUP(B8,Betas!$B:$H,3,FALSE),0) -> 1.214 | F8: =iferror(VLOOKUP(B8,Betas!$B:$H,4,FALSE),0) -> -0.703 | G8: =iferror(VLOOKUP(B8,Betas!$B:$H,5,FALSE),0) -> -1.395 | H8: =iferror(VLOOKUP(B8,Betas!$B:$H,6,FALSE),0) -> 0.004 | I8: =D8/SUM($D$3:$D$67) -> 0.0098010919 | J8: =IFERROR(D8 / XLOOKUP(C8, $M:$M, $R:$R), 0) -> 0.19094584 | M8: Nuclear | N8: {=SUMPRODUCT(($C$4:$C$999=M8)*IFERROR($E$4:$E$999*$J$4:$J$999,0))} -> 0.98209569 | O8: {=SUMPRODUCT(($C$4:$C$999=M8)*IFERROR($F$4:$F$999*$J$4:$J$999,0))} -> 0.43101235 | P8: {=SUMPRODUCT(($C$4:$C$999=M8)*IFERROR($G$4:$G$999*$J$4:$J$999,0))} -> 1.1420347 | Q8: {=SUMPRODUCT(($C$4:$C$999=M8)*IFERROR($H$4:$H$999*$J$4:$J$999,0))} -> 0.51883453 | R8: =SUMIFS($D$3:$D$67,$C$3:$C$67,M8) -> 26115.18
A9: Corporation | B9: AMGN | C9: =VLOOKUP(B9,Subsector!$A:$B,2,FALSE) -> Silver | D9: =iferror(vlookup(B9,'Portfolio Positions'!$A:$F,4,false),0) -> 8255.2 | E9: =iferror(VLOOKUP(B9,Betas!$B:$H,3,FALSE),0) -> 0.85 | F9: =iferror(VLOOKUP(B9,Betas!$B:$H,4,FALSE),0) -> 0.256 | G9: =iferror(VLOOKUP(B9,Betas!$B:$H,5,FALSE),0) -> -0.659 | H9: =iferror(VLOOKUP(B9,Betas!$B:$H,6,FALSE),0) -> -0.061 | I9: =D9/SUM($D$3:$D$67) -> 0.012104878 | J9: =IFERROR(D9 / XLOOKUP(C9, $M:$M, $R:$R), 0) -> 0.13986656 | M9: Payments | N9: {=SUMPRODUCT(($C$4:$C$999=M9)*IFERROR($E$4:$E$999*$J$4:$J$999,0))} -> 1.0689293 | O9: {=SUMPRODUCT(($C$4:$C$999=M9)*IFERROR($F$4:$F$999*$J$4:$J$999,0))} -> 0.35435158 | P9: {=SUMPRODUCT(($C$4:$C$999=M9)*IFERROR($G$4:$G$999*$J$4:$J$999,0))} -> -1.1860926 | Q9: {=SUMPRODUCT(($C$4:$C$999=M9)*IFERROR($H$4:$H$999*$J$4:$J$999,0))} -> 1.1405714 | R9: =SUMIFS($D$3:$D$67,$C$3:$C$67,M9) -> 18682.6
A10: Corporation | B10: APLD | C10: =VLOOKUP(B10,Subsector!$A:$B,2,FALSE) -> Digital Infra | D10: =iferror(vlookup(B10,'Portfolio Positions'!$A:$F,4,false),0) -> 7319.96 | E10: =iferror(VLOOKUP(B10,Betas!$B:$H,3,FALSE),0) -> 2.777 | F10: =iferror(VLOOKUP(B10,Betas!$B:$H,4,FALSE),0) -> -2.63 | G10: =iferror(VLOOKUP(B10,Betas!$B:$H,5,FALSE),0) -> 7.152 | H10: =iferror(VLOOKUP(B10,Betas!$B:$H,6,FALSE),0) -> -5.54 | I10: =D10/SUM($D$3:$D$67) -> 0.010733504 | J10: =IFERROR(D10 / XLOOKUP(C10, $M:$M, $R:$R), 0) -> 0.075759044 | M10: Security | N10: {=SUMPRODUCT(($C$4:$C$999=M10)*IFERROR($E$4:$E$999*$J$4:$J$999,0))} -> 0.87114872 | O10: {=SUMPRODUCT(($C$4:$C$999=M10)*IFERROR($F$4:$F$999*$J$4:$J$999,0))} -> 0.14012431 | P10: {=SUMPRODUCT(($C$4:$C$999=M10)*IFERROR($G$4:$G$999*$J$4:$J$999,0))} -> 0.072693717 | Q10: {=SUMPRODUCT(($C$4:$C$999=M10)*IFERROR($H$4:$H$999*$J$4:$J$999,0))} -> -0.21596139 | R10: =SUMIFS($D$3:$D$67,$C$3:$C$67,M10) -> 35005.11
A11: Corporation | B11: AWK | C11: =VLOOKUP(B11,Subsector!$A:$B,2,FALSE) -> Digital Infra | D11: =iferror(vlookup(B11,'Portfolio Positions'!$A:$F,4,false),0) -> 8559.58 | E11: =iferror(VLOOKUP(B11,Betas!$B:$H,3,FALSE),0) -> -0.196 | F11: =iferror(VLOOKUP(B11,Betas!$B:$H,4,FALSE),0) -> 0.175 | G11: =iferror(VLOOKUP(B11,Betas!$B:$H,5,FALSE),0) -> -0.837 | H11: =iferror(VLOOKUP(B11,Betas!$B:$H,6,FALSE),0) -> 0.233 | I11: =D11/SUM($D$3:$D$67) -> 0.012551201 | J11: =IFERROR(D11 / XLOOKUP(C11, $M:$M, $R:$R), 0) -> 0.08858868 | M11: Silver | N11: {=SUMPRODUCT(($C$4:$C$999=M11)*IFERROR($E$4:$E$999*$J$4:$J$999,0))} -> 0.66421166 | O11: {=SUMPRODUCT(($C$4:$C$999=M11)*IFERROR($F$4:$F$999*$J$4:$J$999,0))} -> 0.31700827 | P11: {=SUMPRODUCT(($C$4:$C$999=M11)*IFERROR($G$4:$G$999*$J$4:$J$999,0))} -> -0.43761064 | Q11: {=SUMPRODUCT(($C$4:$C$999=M11)*IFERROR($H$4:$H$999*$J$4:$J$999,0))} -> 0.097978284 | R11: =SUMIFS($D$3:$D$67,$C$3:$C$67,M11) -> 59021.97
A12: Corporation | B12: AXP | C12: =VLOOKUP(B12,Subsector!$A:$B,2,FALSE) -> Payments | D12: =iferror(vlookup(B12,'Portfolio Positions'!$A:$F,4,false),0) -> 3886.98 | E12: =iferror(VLOOKUP(B12,Betas!$B:$H,3,FALSE),0) -> 1.65 | F12: =iferror(VLOOKUP(B12,Betas!$B:$H,4,FALSE),0) -> 0.683 | G12: =iferror(VLOOKUP(B12,Betas!$B:$H,5,FALSE),0) -> -0.967 | H12: =iferror(VLOOKUP(B12,Betas!$B:$H,6,FALSE),0) -> 0.534 | I12: =D12/SUM($D$3:$D$67) -> 0.0056996099 | J12: =IFERROR(D12 / XLOOKUP(C12, $M:$M, $R:$R), 0) -> 0.20805348 | M12: Waste | N12: {=SUMPRODUCT(($C$4:$C$999=M12)*IFERROR($E$4:$E$999*$J$4:$J$999,0))} -> 0.8153752 | O12: {=SUMPRODUCT(($C$4:$C$999=M12)*IFERROR($F$4:$F$999*$J$4:$J$999,0))} -> 0.50105858 | P12: {=SUMPRODUCT(($C$4:$C$999=M12)*IFERROR($G$4:$G$999*$J$4:$J$999,0))} -> -0.49681101 | Q12: {=SUMPRODUCT(($C$4:$C$999=M12)*IFERROR($H$4:$H$999*$J$4:$J$999,0))} -> -0.16451659 | R12: =SUMIFS($D$3:$D$67,$C$3:$C$67,M12) -> 47650.2
A13: Corporation | B13: BABA | C13: =VLOOKUP(B13,Subsector!$A:$B,2,FALSE) -> AI-Industrial | D13: =iferror(vlookup(B13,'Portfolio Positions'!$A:$F,4,false),0) -> 3730.5 | E13: =iferror(VLOOKUP(B13,Betas!$B:$H,3,FALSE),0) -> 1.068 | F13: =iferror(VLOOKUP(B13,Betas!$B:$H,4,FALSE),0) -> 0.537 | G13: =iferror(VLOOKUP(B13,Betas!$B:$H,5,FALSE),0) -> 0.874 | H13: =iferror(VLOOKUP(B13,Betas!$B:$H,6,FALSE),0) -> -0.997 | I13: =D13/SUM($D$3:$D$67) -> 0.005470158 | J13: =IFERROR(D13 / XLOOKUP(C13, $M:$M, $R:$R), 0) -> 0.064822311 | M13: Thematic Portfolio (exc SPY) | N13: =SUMPRODUCT(E4:E67,$I$4:$I$67) -> 0.7018496 | O13: =SUMPRODUCT(F4:F67,$I$4:$I$67) -> 0.07900479 | P13: =SUMPRODUCT(G4:G67,$I$4:$I$67) -> 0.58050613 | Q13: =SUMPRODUCT(H4:H67,$I$4:$I$67) -> -0.27318982 | R13: =SUM(R4:R12) -> 420530.99
A14: Corporation | B14: BE | C14: =VLOOKUP(B14,Subsector!$A:$B,2,FALSE) -> AI-Industrial | D14: =iferror(vlookup(B14,'Portfolio Positions'!$A:$F,4,false),0) -> 2559.38 | E14: =iferror(VLOOKUP(B14,Betas!$B:$H,3,FALSE),0) -> 3.276 | F14: =iferror(VLOOKUP(B14,Betas!$B:$H,4,FALSE),0) -> 0.624 | G14: =iferror(VLOOKUP(B14,Betas!$B:$H,5,FALSE),0) -> 7.641 | H14: =iferror(VLOOKUP(B14,Betas!$B:$H,6,FALSE),0) -> -2.32 | I14: =D14/SUM($D$3:$D$67) -> 0.0037529052 | J14: =IFERROR(D14 / XLOOKUP(C14, $M:$M, $R:$R), 0) -> 0.044472571
A15: Corporation | B15: BWXT | C15: =VLOOKUP(B15,Subsector!$A:$B,2,FALSE) -> Nuclear | D15: =iferror(vlookup(B15,'Portfolio Positions'!$A:$F,4,false),0) -> 9666.52 | E15: =iferror(VLOOKUP(B15,Betas!$B:$H,3,FALSE),0) -> 1.447 | F15: =iferror(VLOOKUP(B15,Betas!$B:$H,4,FALSE),0) -> -0.268 | G15: =iferror(VLOOKUP(B15,Betas!$B:$H,5,FALSE),0) -> 2.956 | H15: =iferror(VLOOKUP(B15,Betas!$B:$H,6,FALSE),0) -> -0.298 | I15: =D15/SUM($D$3:$D$67) -> 0.014174344 | J15: =IFERROR(D15 / XLOOKUP(C15, $M:$M, $R:$R), 0) -> 0.37014947
A16: Corporation | B16: CIEN | C16: =VLOOKUP(B16,Subsector!$A:$B,2,FALSE) -> Digital Infra | D16: =iferror(vlookup(B16,'Portfolio Positions'!$A:$F,4,false),0) -> 16162.92 | E16: =iferror(VLOOKUP(B16,Betas!$B:$H,3,FALSE),0) -> 1.25 | F16: =iferror(VLOOKUP(B16,Betas!$B:$H,4,FALSE),0) -> -0.803 | G16: =iferror(VLOOKUP(B16,Betas!$B:$H,5,FALSE),0) -> 6.63 | H16: =iferror(VLOOKUP(B16,Betas!$B:$H,6,FALSE),0) -> -2.335 | I16: =D16/SUM($D$3:$D$67) -> 0.023700235 | J16: =IFERROR(D16 / XLOOKUP(C16, $M:$M, $R:$R), 0) -> 0.16728061
A17: Corporation | B17: CLH | C17: =VLOOKUP(B17,Subsector!$A:$B,2,FALSE) -> Waste | D17: =iferror(vlookup(B17,'Portfolio Positions'!$A:$F,4,false),0) -> 9739.28 | E17: =iferror(VLOOKUP(B17,Betas!$B:$H,3,FALSE),0) -> 1.164 | F17: =iferror(VLOOKUP(B17,Betas!$B:$H,4,FALSE),0) -> 0.274 | G17: =iferror(VLOOKUP(B17,Betas!$B:$H,5,FALSE),0) -> -0.187 | H17: =iferror(VLOOKUP(B17,Betas!$B:$H,6,FALSE),0) -> -0.446 | I17: =D17/SUM($D$3:$D$67) -> 0.014281035 | J17: =IFERROR(D17 / XLOOKUP(C17, $M:$M, $R:$R), 0) -> 0.20439117
A18: Corporation | B18: CSIQ | C18: =VLOOKUP(B18,Subsector!$A:$B,2,FALSE) -> AI-Industrial | D18: =iferror(vlookup(B18,'Portfolio Positions'!$A:$F,4,false),0) -> 0 | E18: =iferror(VLOOKUP(B18,Betas!$B:$H,3,FALSE),0) -> 0 | F18: =iferror(VLOOKUP(B18,Betas!$B:$H,4,FALSE),0) -> 0 | G18: =iferror(VLOOKUP(B18,Betas!$B:$H,5,FALSE),0) -> 0 | H18: =iferror(VLOOKUP(B18,Betas!$B:$H,6,FALSE),0) -> 0 | I18: =D18/SUM($D$3:$D$67) -> 0 | J18: =IFERROR(D18 / XLOOKUP(C18, $M:$M, $R:$R), 0) -> 0
A19: Corporation | B19: DAR | C19: =VLOOKUP(B19,Subsector!$A:$B,2,FALSE) -> Waste | D19: =iferror(vlookup(B19,'Portfolio Positions'!$A:$F,4,false),0) -> 13275.84 | E19: =iferror(VLOOKUP(B19,Betas!$B:$H,3,FALSE),0) -> 1.172 | F19: =iferror(VLOOKUP(B19,Betas!$B:$H,4,FALSE),0) -> 1.257 | G19: =iferror(VLOOKUP(B19,Betas!$B:$H,5,FALSE),0) -> 0.394 | H19: =iferror(VLOOKUP(B19,Betas!$B:$H,6,FALSE),0) -> -0.48 | I19: =D19/SUM($D$3:$D$67) -> 0.019466812 | J19: =IFERROR(D19 / XLOOKUP(C19, $M:$M, $R:$R), 0) -> 0.27861037
A20: Corporation | B20: DBRG | C20: =VLOOKUP(B20,Subsector!$A:$B,2,FALSE) -> Digital Infra | D20: =iferror(vlookup(B20,'Portfolio Positions'!$A:$F,4,false),0) -> 8401.08 | E20: =iferror(VLOOKUP(B20,Betas!$B:$H,3,FALSE),0) -> 0.317 | F20: =iferror(VLOOKUP(B20,Betas!$B:$H,4,FALSE),0) -> -1.028 | G20: =iferror(VLOOKUP(B20,Betas!$B:$H,5,FALSE),0) -> 1.474 | H20: =iferror(VLOOKUP(B20,Betas!$B:$H,6,FALSE),0) -> -2.872 | I20: =D20/SUM($D$3:$D$67) -> 0.012318787 | J20: =IFERROR(D20 / XLOOKUP(C20, $M:$M, $R:$R), 0) -> 0.08694826
A21: Corporation | B21: DIS | C21: =VLOOKUP(B21,Subsector!$A:$B,2,FALSE) -> Adtech | D21: =iferror(vlookup(B21,'Portfolio Positions'!$A:$F,4,false),0) -> 3717.07 | E21: =iferror(VLOOKUP(B21,Betas!$B:$H,3,FALSE),0) -> 1.354 | F21: =iferror(VLOOKUP(B21,Betas!$B:$H,4,FALSE),0) -> 0.812 | G21: =iferror(VLOOKUP(B21,Betas!$B:$H,5,FALSE),0) -> -1.266 | H21: =iferror(VLOOKUP(B21,Betas!$B:$H,6,FALSE),0) -> 0.058 | I21: =D21/SUM($D$3:$D$67) -> 0.0054504651 | J21: =IFERROR(D21 / XLOOKUP(C21, $M:$M, $R:$R), 0) -> 1
A22: Corporation | B22: DLR | C22: =VLOOKUP(B22,Subsector!$A:$B,2,FALSE) -> Digital Infra | D22: =iferror(vlookup(B22,'Portfolio Positions'!$A:$F,4,false),0) -> 8740.47 | E22: =iferror(VLOOKUP(B22,Betas!$B:$H,3,FALSE),0) -> 0.802 | F22: =iferror(VLOOKUP(B22,Betas!$B:$H,4,FALSE),0) -> 0.013 | G22: =iferror(VLOOKUP(B22,Betas!$B:$H,5,FALSE),0) -> 0.568 | H22: =iferror(VLOOKUP(B22,Betas!$B:$H,6,FALSE),0) -> -0.188 | I22: =D22/SUM($D$3:$D$67) -> 0.012816446 | J22: =IFERROR(D22 / XLOOKUP(C22, $M:$M, $R:$R), 0) -> 0.090460829
A23: Corporation | B23: DXCM | C23: =VLOOKUP(B23,Subsector!$A:$B,2,FALSE) -> Silver | D23: =iferror(vlookup(B23,'Portfolio Positions'!$A:$F,4,false),0) -> 4470.61 | E23: =iferror(VLOOKUP(B23,Betas!$B:$H,3,FALSE),0) -> 0.962 | F23: =iferror(VLOOKUP(B23,Betas!$B:$H,4,FALSE),0) -> 0.112 | G23: =iferror(VLOOKUP(B23,Betas!$B:$H,5,FALSE),0) -> 0.34 | H23: =iferror(VLOOKUP(B23,Betas!$B:$H,6,FALSE),0) -> -0.022 | I23: =D23/SUM($D$3:$D$67) -> 0.0065554062 | J23: =IFERROR(D23 / XLOOKUP(C23, $M:$M, $R:$R), 0) -> 0.075744846
A24: Corporation | B24: EHAB | C24: =VLOOKUP(B24,Subsector!$A:$B,2,FALSE) -> Silver | D24: =iferror(vlookup(B24,'Portfolio Positions'!$A:$F,4,false),0) -> 0 | E24: =iferror(VLOOKUP(B24,Betas!$B:$H,3,FALSE),0) -> 0 | F24: =iferror(VLOOKUP(B24,Betas!$B:$H,4,FALSE),0) -> 0 | G24: =iferror(VLOOKUP(B24,Betas!$B:$H,5,FALSE),0) -> 0 | H24: =iferror(VLOOKUP(B24,Betas!$B:$H,6,FALSE),0) -> 0 | I24: =D24/SUM($D$3:$D$67) -> 0 | J24: =IFERROR(D24 / XLOOKUP(C24, $M:$M, $R:$R), 0) -> 0
A25: Corporation | B25: EQIX | C25: =VLOOKUP(B25,Subsector!$A:$B,2,FALSE) -> Digital Infra | D25: =iferror(vlookup(B25,'Portfolio Positions'!$A:$F,4,false),0) -> 10486.47 | E25: =iferror(VLOOKUP(B25,Betas!$B:$H,3,FALSE),0) -> 0.425 | F25: =iferror(VLOOKUP(B25,Betas!$B:$H,4,FALSE),0) -> 0.126 | G25: =iferror(VLOOKUP(B25,Betas!$B:$H,5,FALSE),0) -> 0.269 | H25: =iferror(VLOOKUP(B25,Betas!$B:$H,6,FALSE),0) -> 0.126 | I25: =D25/SUM($D$3:$D$67) -> 0.015376665 | J25: =IFERROR(D25 / XLOOKUP(C25, $M:$M, $R:$R), 0) -> 0.10853132
... A67: Corporation | B67: XYZ | C67: =VLOOKUP(B67,Subsector!$A:$B,2,FALSE) -> Payments | D67: =iferror(vlookup(B67,'Portfolio Positions'!$A:$F,4,false),0) -> 0 | E67: =iferror(VLOOKUP(B67,Betas!$B:$H,3,FALSE),0) -> 1.3357 | F67: =iferror(VLOOKUP(B67,Betas!$B:$H,4,FALSE),0) -> -0.2139 | G67: =iferror(VLOOKUP(B67,Betas!$B:$H,5,FALSE),0) -> -0.0164 | H67: =iferror(VLOOKUP(B67,Betas!$B:$H,6,FALSE),0) -> 0.2497 | I67: =D67/SUM($D$3:$D$67) -> 0 | J67: =IFERROR(D67 / XLOOKUP(C67, $M:$M, $R:$R), 0) -> 0
I68: =SUM(I3:I67) -> 1

Sheet Portfolio Positions
A1: Symbol | B1: Subtheme | C1: Weight | D1: Current Value | E1: Total Gain / Loss | F1: Total Gain / Loss %
A2: DIS | B2: Adtech | C2: 0.0046 | D2: 3717.07 | E2: -282.91 | F2: -0.0707
A3: BABA | B3: AI-Industrial | C3: 0.0046 | D3: 3730.5 | E3: -976.5 | F3: -0.2075
A4: BE | B4: AI-Industrial | C4: 0.0032 | D4: 2559.38 | E4: 712.66 | F4: 0.3859
A5: GOOG | B5: AI-Industrial | C5: 0.0055 | D5: 4399.95 | E5: -323.4 | F5: -0.0685
A6: IREN | B6: AI-Industrial | C6: 0.0058 | D6: 4669.44 | E6: -139.02 | F6: -0.029
A7: LITE | B7: AI-Industrial | C7: 0.0267 | D7: 21512.68 | E7: 9381.6 | F7: 0.7733
A8: NBIS | B8: AI-Industrial | C8: 0.0074 | D8: 5961.79 | E8: 1122.62 | F8: 0.2319
A9: NVDA | B9: AI-Industrial | C9: 0.0059 | D9: 4714.6 | E9: -141.81 | F9: -0.0292
A10: TSLA | B10: AI-Industrial | C10: 0.0053 | D10: 4229.28 | E10: -591.78 | F10: -0.1228
A11: TSM | B11: AI-Industrial | C11: 0.0072 | D11: 5772.01 | E11: 876.73 | F11: 0.179
A12: BE | B12: Battery | C12: 0.0051 | D12: 4128.04 | E12: 1149.45 | F12: 0.3859
A13: APLD | B13: Digital Infra | C13: 0.0091 | D13: 7319.96 | E13: -780.03 | F13: -0.0963
... A66: WTS | B66: Water PFAS | C66: 0.0148 | D66: 11944.84 | E66: -288.01 | F66: -0.0236
A67: SPY | B67: SPY | C67: 0.3317 | D67: =B70*B71 -> 261442
A70: SPY Price | B70: 649.71
A71: SPY Shares | B71: 402.398

Sheet Betas
B1: ticker | C1: alpha | D1: beta_market | E1: beta_value | F1: beta_momentum | G1: beta_growth | H1: R^2
A2: 1 | B2: ABBV | C2: -25.7 | D2: 0.146 | E2: -0.101 | F2: 0.123 | G2: 0.367 | H2: 25.3
A3: 2 | B3: ABNB | C3: 80.1 | D3: 1.385 | E3: -0.919 | F3: -1.328 | G3: -0.005 | H3: 25.1
A4: 3 | B4: ABT | C4: -56.7 | D4: 0.649 | E4: 0.68 | F4: -0.548 | G4: 0.372 | H4: 25.4
A5: 4 | B5: ADUS | C5: -50.5 | D5: 0.679 | E5: 1.071 | F5: -0.478 | G5: 0.218 | H5: 30.7
A6: 5 | B6: ALRM | C6: 19.5 | D6: 1.214 | E6: -0.703 | F6: -1.395 | G6: 0.004 | H6: 24.6
A7: 6 | B7: AMGN | C7: 22.9 | D7: 0.85 | E7: 0.256 | F7: -0.659 | G7: -0.061 | H7: 27
A8: 7 | B8: APLD | C8: 54.5 | D8: 2.777 | E8: -2.63 | F8: 7.152 | G8: -5.54 | H8: 86.6
A9: 8 | B9: AWK | C9: 17.2 | D9: -0.196 | E9: 0.175 | F9: -0.837 | G9: 0.233 | H9: 20.8
A10: 9 | B10: AXP | C10: -46 | D10: 1.65 | E10: 0.683 | F10: -0.967 | G10: 0.534 | H10: 24.9
A11: 10 | B11: BABA | C11: -85.4 | D11: 1.068 | E11: 0.537 | F11: 0.874 | G11: -0.997 | H11: 37.7
A12: 11 | B12: BE | C12: 48.6 | D12: 3.276 | E12: 0.624 | F12: 7.641 | G12: -2.32 | H12: 79.4
A13: 12 | B13: BMI | C13: -30.9 | D13: 1.641 | E13: 0.49 | F13: -1.712 | G13: 0.396 | H13: 34.5
... A67: 66 | B67: SPY | C67: 0 | D67: 0.998 | E67: -0.002 | F67: 0.002 | G67: -0.004 | H67: 0.3

Sheet Subsector
A1: Symbol | B1: Subtheme | C1: Weights | D1: Current Value | E1: Total Gain/Loss $ | F1: Total Gain/Loss %
A2: ABBV | B2: Silver | C2: 0.005 | D2: 4152.41 | E2: 141.6 | F2: 0.0353
A3: ABNB | B3: Experientials | C3: 0.0098 | D3: 8092.34 | E3: 92.4 | F3: 0.0115
A4: ABT | B4: Silver | C4: 0.0045 | D4: 3709.31 | E4: -301.53 | F4: -0.0752
A5: ADUS | B5: Silver | C5: 0.0066 | D5: 5491.41 | E5: 133.51 | F5: 0.0249
A6: AFRM | B6: Payments | C6: 0.0072 | D6: 5938.59 | E6: -2061.41 | F6: -0.2577
A7: ALRM | B7: Security | C7: 0.0085 | D7: 7039.23 | E7: -960.76 | F7: -0.1201
A8: AMGN | B8: Silver | C8: 0.0056 | D8: 4660.28 | E8: 629.68 | F8: 0.1562
A9: APLD | B9: Digital Infra | C9: 0.0118 | D9: 9793.26 | E9: 1693.27 | F9: 0.209
A10: AWK | B10: Digital Infra | C10: 0.01 | D10: 8309.97 | E10: 309.98 | F10: 0.0387
A11: AXP | B11: Payments | C11: 0.0053 | D11: 4358.47 | E11: -120.68 | F11: -0.027
A12: BABA | B12: AI-Industrial | C12: 0.0056 | D12: 4671.9 | E12: -35.1 | F12: -0.0075
A13: BE | B13: AI-Industrial | C13: 0.0031 | D13: 2578.95 | E13: 732.22 | F13: 0.3965
... A75: XYZ | B75: Payments | C75: 0.0076 | D75: 6320.66 | E75: -1679.33 | F75: -0.21
A76: SPY | B76: Benchmark
